smart_env/__init__.py
smart_env/apps.py
smart_env/checks.py
smart_env/exceptions.py
smart_env/version.py
smart_env/management/__init__.py
smart_env/management/commands/__init__.py
smart_env/management/commands/env.py
django_smart_env-1.0.dist-info/METADATA
django_smart_env-1.0.dist-info/WHEEL
django_smart_env-1.0.dist-info/RECORD
